bamsnap/__init__.py
bamsnap/_logging.py
bamsnap/_options.py
bamsnap/bam.py
bamsnap/bamsnap.py
bamsnap/basetrack.py
bamsnap/conf.py
bamsnap/coordinates.py
bamsnap/drawread.py
bamsnap/drawreadset.py
bamsnap/geneplot.py
bamsnap/scale.py
bamsnap/util.py
bamsnap/data/Homo_sapiens.GRCh37.bed.gz
bamsnap/data/Homo_sapiens.GRCh37.bed.gz.tbi
bamsnap/data/Homo_sapiens.GRCh38.bed.gz
bamsnap/data/Homo_sapiens.GRCh38.bed.gz.tbi
bamsnap/data/conf.json
bamsnap/data/preproc_EnsembleGene_gtf2bed.py
bamsnap/templates/VeraMono-Bold.ttf
bamsnap/templates/VeraMono.ttf
bamsnap/templates/__init__.py
bamsnap/templates/bamsnap_index.html
bamsnap/templates/bootstrap.bundle.min.js
bamsnap/templates/bootstrap.bundle.min.js.map
bamsnap/templates/bootstrap.min.css
bamsnap/templates/bootstrap.min.css.map
bamsnap/templates/sample_list.html
bamsnap/templates/sample_temp.html
bamsnap/templates/template.html
bamsnap/templates/variant_list.html
bamsnap/templates/variant_temp.html
bamsnap_cgap-0.3.0.dist-info/LICENSE
bamsnap_cgap-0.3.0.dist-info/METADATA
bamsnap_cgap-0.3.0.dist-info/WHEEL
bamsnap_cgap-0.3.0.dist-info/entry_points.txt
bamsnap_cgap-0.3.0.dist-info/top_level.txt
bamsnap_cgap-0.3.0.dist-info/RECORD
