Metadata-Version: 2.1
Name: bamsnap-cgap
Version: 0.3.0
Summary: A converter from .bam to .png for specific genomic region.
Home-page: https://github.com/danielmsk/bamsnap
Author: Daniel Minseok Kwon, CGAP team
License: MIT
Keywords: genomics,bioinformatics
Platform: UNKNOWN
Classifier: Operating System :: OS Independent
Classifier: Topic :: Software Development :: Libraries
Classifier: License :: OSI Approved :: MIT License
Classifier: Programming Language :: Python :: 3.4
Classifier: Programming Language :: Python :: 3.5
Classifier: Programming Language :: Python :: 3.6
Requires-Dist: pyfaidx (>=0.5.3.1)
Requires-Dist: pysam (>=0.11.2.2)
Requires-Dist: Pillow (>=2.0.0)
Requires-Dist: pytabix (>=0.0.2)
